plankton/__init__.py
plankton/graph.py
plankton/pixelmaps.py
plankton/plankton.py
plankton/ssam.py
plankton/stats.py
plankton/utils.py
planktonspace-0.0.12.dist-info/LICENSE
planktonspace-0.0.12.dist-info/METADATA
planktonspace-0.0.12.dist-info/WHEEL
planktonspace-0.0.12.dist-info/top_level.txt
planktonspace-0.0.12.dist-info/RECORD
