Metadata-Version: 2.1
Name: planktonspace
Version: 0.0.12
Summary: A point process analysis package
Author-email: Sebastian Tiesmeyer <sebastian.tiesmeyer@bih-charite.de>
License: MIT License
Project-URL: Homepage, https://github.com/HiDiHlabs/planktonpy
Project-URL: Bug Tracker, https://github.com/HiDiHlabs/planktonpy
Classifier: Programming Language :: Python :: 3
Classifier: License :: OSI Approved :: MIT License
Classifier: Operating System :: OS Independent
Requires-Python: >=3.7
License-File: LICENSE
Requires-Dist: numpy
Requires-Dist: anndata
Requires-Dist: scanpy
Requires-Dist: jupyter
Requires-Dist: matplotlib
Requires-Dist: pandas
Requires-Dist: plotly
Requires-Dist: scipy
Requires-Dist: scikit-image
Requires-Dist: scikit-learn
Requires-Dist: umap-learn
Requires-Dist: python-louvain
